{
  "version": "3.5.0",
  "buildDate": "2025-01-31",
  "author": "Universal Development Team",
  "description": "Universal Automation Toolkit v3.5 - Advanced AI & Enterprise Integration Enhanced",
  "features": {
    "ai": {
      "enabled": true,
      "multiModal": true,
      "quantum": true,
      "enterprise": true,
      "uiux": true,
      "advanced": true,
      "migration": true,
      "backup": true
    },
    "automation": {
      "projectScanner": true,
      "universalManager": true,
      "aiFeatures": true,
      "testing": true,
      "build": true,
      "deployment": true,
      "monitoring": true,
      "optimization": true
    }
  },
  "settings": {
    "verbose": false,
    "generateReports": true,
    "enableLogging": true,
    "parallelProcessing": true,
    "autoBackup": true,
    "performanceMonitoring": true
  },
  "performance": {
    "maxConcurrentTasks": 10,
    "memoryLimit": "2GB",
    "timeout": 300,
    "retryAttempts": 3
  }
}
